{
    "schemes": [
        "http",
        "https"
    ],
    "swagger": "2.0",
    "info": {
        "description": "API for ValoMapper backend services.",
        "title": "ValoMapper API",
        "contact": {},
        "version": "1.0"
    },
    "basePath": "/",
    "paths": {
        "/api/auth/rso/callback": {
            "post": {
                "description": "Exchanges a Riot authorization code and returns a Firebase custom token plus user data.",
                "consumes": [
                    "application/json"
                ],
                "produces": [
                    "application/json"
                ],
                "tags": [
                    "auth"
                ],
                "summary": "Exchange RSO code for Firebase custom token",
                "parameters": [
                    {
                        "description": "RSO authorization code",
                        "name": "request",
                        "in": "body",
                        "required": true,
                        "schema": {
                            "$ref": "#/definitions/handlers.RSORequest"
                        }
                    }
                ],
                "responses": {
                    "200": {
                        "description": "OK",
                        "schema": {
                            "$ref": "#/definitions/handlers.RSOCallbackResponse"
                        }
                    },
                    "400": {
                        "description": "Bad Request",
                        "schema": {
                            "$ref": "#/definitions/handlers.ErrorResponse"
                        }
                    },
                    "401": {
                        "description": "Unauthorized",
                        "schema": {
                            "$ref": "#/definitions/handlers.ErrorResponse"
                        }
                    },
                    "500": {
                        "description": "Internal Server Error",
                        "schema": {
                            "$ref": "#/definitions/handlers.ErrorResponse"
                        }
                    }
                }
            }
        },
        "/api/billing/cancel-subscription": {
            "post": {
                "security": [
                    {
                        "BearerAuth": []
                    }
                ],
                "description": "Schedules cancellation at period end for the authenticated user's active subscription.",
                "produces": [
                    "application/json"
                ],
                "tags": [
                    "billing"
                ],
                "summary": "Cancel current subscription",
                "responses": {
                    "200": {
                        "description": "OK",
                        "schema": {
                            "$ref": "#/definitions/handlers.CancelSubscriptionResponse"
                        }
                    },
                    "400": {
                        "description": "Bad Request",
                        "schema": {
                            "$ref": "#/definitions/handlers.ErrorResponse"
                        }
                    },
                    "401": {
                        "description": "Unauthorized",
                        "schema": {
                            "$ref": "#/definitions/handlers.ErrorResponse"
                        }
                    },
                    "404": {
                        "description": "Not Found",
                        "schema": {
                            "$ref": "#/definitions/handlers.ErrorResponse"
                        }
                    },
                    "500": {
                        "description": "Internal Server Error",
                        "schema": {
                            "$ref": "#/definitions/handlers.ErrorResponse"
                        }
                    }
                }
            }
        },
        "/api/billing/checkout-session": {
            "post": {
                "security": [
                    {
                        "BearerAuth": []
                    }
                ],
                "description": "Creates a Stripe checkout session for a monthly or yearly plan.",
                "consumes": [
                    "application/json"
                ],
                "produces": [
                    "application/json"
                ],
                "tags": [
                    "billing"
                ],
                "summary": "Create Stripe checkout session",
                "parameters": [
                    {
                        "description": "Checkout request",
                        "name": "request",
                        "in": "body",
                        "schema": {
                            "$ref": "#/definitions/handlers.CreateCheckoutSessionRequest"
                        }
                    }
                ],
                "responses": {
                    "200": {
                        "description": "OK",
                        "schema": {
                            "$ref": "#/definitions/handlers.CreateCheckoutSessionResponse"
                        }
                    },
                    "400": {
                        "description": "Bad Request",
                        "schema": {
                            "$ref": "#/definitions/handlers.ErrorResponse"
                        }
                    },
                    "401": {
                        "description": "Unauthorized",
                        "schema": {
                            "$ref": "#/definitions/handlers.ErrorResponse"
                        }
                    },
                    "409": {
                        "description": "Conflict",
                        "schema": {
                            "$ref": "#/definitions/handlers.ErrorResponse"
                        }
                    },
                    "500": {
                        "description": "Internal Server Error",
                        "schema": {
                            "$ref": "#/definitions/handlers.ErrorResponse"
                        }
                    }
                }
            }
        },
        "/api/billing/plans": {
            "get": {
                "description": "Returns Stripe-backed monthly and yearly pricing details.",
                "produces": [
                    "application/json"
                ],
                "tags": [
                    "billing"
                ],
                "summary": "Get billing plans",
                "responses": {
                    "200": {
                        "description": "OK",
                        "schema": {
                            "$ref": "#/definitions/handlers.BillingPlansResponse"
                        }
                    },
                    "500": {
                        "description": "Internal Server Error",
                        "schema": {
                            "$ref": "#/definitions/handlers.ErrorResponse"
                        }
                    }
                }
            }
        },
        "/api/billing/resume-subscription": {
            "post": {
                "security": [
                    {
                        "BearerAuth": []
                    }
                ],
                "description": "Removes a scheduled cancellation from the authenticated user's active subscription.",
                "produces": [
                    "application/json"
                ],
                "tags": [
                    "billing"
                ],
                "summary": "Resume current subscription",
                "responses": {
                    "200": {
                        "description": "OK",
                        "schema": {
                            "$ref": "#/definitions/handlers.CancelSubscriptionResponse"
                        }
                    },
                    "400": {
                        "description": "Bad Request",
                        "schema": {
                            "$ref": "#/definitions/handlers.ErrorResponse"
                        }
                    },
                    "401": {
                        "description": "Unauthorized",
                        "schema": {
                            "$ref": "#/definitions/handlers.ErrorResponse"
                        }
                    },
                    "500": {
                        "description": "Internal Server Error",
                        "schema": {
                            "$ref": "#/definitions/handlers.ErrorResponse"
                        }
                    }
                }
            }
        },
        "/api/billing/stack/accept/{id}": {
            "post": {
                "security": [
                    {
                        "BearerAuth": []
                    }
                ],
                "description": "Accepts a pending stack invite for the authenticated user and schedules cancellation of any personal Stripe subscription.",
                "produces": [
                    "application/json"
                ],
                "tags": [
                    "billing"
                ],
                "summary": "Accept stack invite",
                "parameters": [
                    {
                        "type": "integer",
                        "description": "Stack invite ID",
                        "name": "id",
                        "in": "path",
                        "required": true
                    }
                ],
                "responses": {
                    "204": {
                        "description": "No Content"
                    },
                    "400": {
                        "description": "Bad Request",
                        "schema": {
                            "$ref": "#/definitions/handlers.ErrorResponse"
                        }
                    },
                    "401": {
                        "description": "Unauthorized",
                        "schema": {
                            "$ref": "#/definitions/handlers.ErrorResponse"
                        }
                    },
                    "403": {
                        "description": "Forbidden",
                        "schema": {
                            "$ref": "#/definitions/handlers.ErrorResponse"
                        }
                    },
                    "404": {
                        "description": "Not Found",
                        "schema": {
                            "$ref": "#/definitions/handlers.ErrorResponse"
                        }
                    },
                    "500": {
                        "description": "Internal Server Error",
                        "schema": {
                            "$ref": "#/definitions/handlers.ErrorResponse"
                        }
                    }
                }
            }
        },
        "/api/billing/stack/decline/{id}": {
            "post": {
                "security": [
                    {
                        "BearerAuth": []
                    }
                ],
                "description": "Declines a specific pending stack invite for the authenticated user.",
                "produces": [
                    "application/json"
                ],
                "tags": [
                    "billing"
                ],
                "summary": "Decline stack invite",
                "parameters": [
                    {
                        "type": "integer",
                        "description": "Stack invite ID",
                        "name": "id",
                        "in": "path",
                        "required": true
                    }
                ],
                "responses": {
                    "204": {
                        "description": "No Content"
                    },
                    "400": {
                        "description": "Bad Request",
                        "schema": {
                            "$ref": "#/definitions/handlers.ErrorResponse"
                        }
                    },
                    "401": {
                        "description": "Unauthorized",
                        "schema": {
                            "$ref": "#/definitions/handlers.ErrorResponse"
                        }
                    },
                    "404": {
                        "description": "Not Found",
                        "schema": {
                            "$ref": "#/definitions/handlers.ErrorResponse"
                        }
                    },
                    "500": {
                        "description": "Internal Server Error",
                        "schema": {
                            "$ref": "#/definitions/handlers.ErrorResponse"
                        }
                    }
                }
            }
        },
        "/api/billing/stack/invite": {
            "post": {
                "security": [
                    {
                        "BearerAuth": []
                    }
                ],
                "description": "Invites a user by Firebase UID to join the authenticated stack owner's plan.",
                "consumes": [
                    "application/json"
                ],
                "produces": [
                    "application/json"
                ],
                "tags": [
                    "billing"
                ],
                "summary": "Invite user to stack",
                "parameters": [
                    {
                        "description": "Invite request",
                        "name": "request",
                        "in": "body",
                        "required": true,
                        "schema": {
                            "$ref": "#/definitions/handlers.InviteStackMemberRequest"
                        }
                    }
                ],
                "responses": {
                    "201": {
                        "description": "Created",
                        "schema": {
                            "$ref": "#/definitions/models.StackMember"
                        }
                    },
                    "400": {
                        "description": "Bad Request",
                        "schema": {
                            "$ref": "#/definitions/handlers.ErrorResponse"
                        }
                    },
                    "401": {
                        "description": "Unauthorized",
                        "schema": {
                            "$ref": "#/definitions/handlers.ErrorResponse"
                        }
                    },
                    "403": {
                        "description": "Forbidden",
                        "schema": {
                            "$ref": "#/definitions/handlers.ErrorResponse"
                        }
                    },
                    "404": {
                        "description": "Not Found",
                        "schema": {
                            "$ref": "#/definitions/handlers.ErrorResponse"
                        }
                    },
                    "409": {
                        "description": "Conflict",
                        "schema": {
                            "$ref": "#/definitions/handlers.ErrorResponse"
                        }
                    },
                    "422": {
                        "description": "Unprocessable Entity",
                        "schema": {
                            "$ref": "#/definitions/handlers.ErrorResponse"
                        }
                    },
                    "500": {
                        "description": "Internal Server Error",
                        "schema": {
                            "$ref": "#/definitions/handlers.ErrorResponse"
                        }
                    }
                }
            }
        },
        "/api/billing/stack/leave": {
            "delete": {
                "security": [
                    {
                        "BearerAuth": []
                    }
                ],
                "description": "Leaves the stack that the authenticated user currently belongs to.",
                "produces": [
                    "application/json"
                ],
                "tags": [
                    "billing"
                ],
                "summary": "Leave current stack",
                "responses": {
                    "204": {
                        "description": "No Content"
                    },
                    "401": {
                        "description": "Unauthorized",
                        "schema": {
                            "$ref": "#/definitions/handlers.ErrorResponse"
                        }
                    },
                    "404": {
                        "description": "Not Found",
                        "schema": {
                            "$ref": "#/definitions/handlers.ErrorResponse"
                        }
                    },
                    "500": {
                        "description": "Internal Server Error",
                        "schema": {
                            "$ref": "#/definitions/handlers.ErrorResponse"
                        }
                    }
                }
            }
        },
        "/api/billing/stack/members": {
            "get": {
                "security": [
                    {
                        "BearerAuth": []
                    }
                ],
                "description": "Returns pending and active stack members for the authenticated stack context. Stack owners and active stack members can view the roster.",
                "produces": [
                    "application/json"
                ],
                "tags": [
                    "billing"
                ],
                "summary": "Get stack members",
                "responses": {
                    "200": {
                        "description": "OK",
                        "schema": {
                            "$ref": "#/definitions/handlers.StackMembersResponse"
                        }
                    },
                    "401": {
                        "description": "Unauthorized",
                        "schema": {
                            "$ref": "#/definitions/handlers.ErrorResponse"
                        }
                    },
                    "403": {
                        "description": "Forbidden",
                        "schema": {
                            "$ref": "#/definitions/handlers.ErrorResponse"
                        }
                    },
                    "500": {
                        "description": "Internal Server Error",
                        "schema": {
                            "$ref": "#/definitions/handlers.ErrorResponse"
                        }
                    }
                }
            }
        },
        "/api/billing/stack/members/{id}": {
            "delete": {
                "security": [
                    {
                        "BearerAuth": []
                    }
                ],
                "description": "Removes a member invite or active member from the authenticated stack owner's stack.",
                "produces": [
                    "application/json"
                ],
                "tags": [
                    "billing"
                ],
                "summary": "Remove stack member",
                "parameters": [
                    {
                        "type": "integer",
                        "description": "Stack member record ID",
                        "name": "id",
                        "in": "path",
                        "required": true
                    }
                ],
                "responses": {
                    "204": {
                        "description": "No Content"
                    },
                    "400": {
                        "description": "Bad Request",
                        "schema": {
                            "$ref": "#/definitions/handlers.ErrorResponse"
                        }
                    },
                    "401": {
                        "description": "Unauthorized",
                        "schema": {
                            "$ref": "#/definitions/handlers.ErrorResponse"
                        }
                    },
                    "403": {
                        "description": "Forbidden",
                        "schema": {
                            "$ref": "#/definitions/handlers.ErrorResponse"
                        }
                    },
                    "404": {
                        "description": "Not Found",
                        "schema": {
                            "$ref": "#/definitions/handlers.ErrorResponse"
                        }
                    },
                    "500": {
                        "description": "Internal Server Error",
                        "schema": {
                            "$ref": "#/definitions/handlers.ErrorResponse"
                        }
                    }
                }
            }
        },
        "/api/billing/stack/pending-invites": {
            "get": {
                "security": [
                    {
                        "BearerAuth": []
                    }
                ],
                "description": "Returns the pending stack invites for the authenticated user.",
                "produces": [
                    "application/json"
                ],
                "tags": [
                    "billing"
                ],
                "summary": "Get pending stack invites",
                "responses": {
                    "200": {
                        "description": "OK",
                        "schema": {
                            "type": "array",
                            "items": {
                                "$ref": "#/definitions/models.StackMember"
                            }
                        }
                    },
                    "401": {
                        "description": "Unauthorized",
                        "schema": {
                            "$ref": "#/definitions/handlers.ErrorResponse"
                        }
                    },
                    "500": {
                        "description": "Internal Server Error",
                        "schema": {
                            "$ref": "#/definitions/handlers.ErrorResponse"
                        }
                    }
                }
            }
        },
        "/api/billing/webhook": {
            "post": {
                "description": "Validates and processes Stripe subscription-related webhook events.",
                "consumes": [
                    "application/json"
                ],
                "produces": [
                    "application/json"
                ],
                "tags": [
                    "billing"
                ],
                "summary": "Stripe webhook receiver",
                "parameters": [
                    {
                        "type": "string",
                        "description": "Stripe webhook signature",
                        "name": "Stripe-Signature",
                        "in": "header",
                        "required": true
                    }
                ],
                "responses": {
                    "200": {
                        "description": "OK",
                        "schema": {
                            "$ref": "#/definitions/handlers.StripeWebhookResponse"
                        }
                    },
                    "400": {
                        "description": "Bad Request",
                        "schema": {
                            "$ref": "#/definitions/handlers.ErrorResponse"
                        }
                    },
                    "500": {
                        "description": "Internal Server Error",
                        "schema": {
                            "$ref": "#/definitions/handlers.ErrorResponse"
                        }
                    }
                }
            }
        },
        "/api/folders": {
            "get": {
                "security": [
                    {
                        "BearerAuth": []
                    }
                ],
                "description": "Lists folders for the authenticated user.",
                "produces": [
                    "application/json"
                ],
                "tags": [
                    "folders"
                ],
                "summary": "List folders",
                "responses": {
                    "200": {
                        "description": "OK",
                        "schema": {
                            "type": "array",
                            "items": {
                                "$ref": "#/definitions/models.Folder"
                            }
                        }
                    },
                    "401": {
                        "description": "Unauthorized",
                        "schema": {
                            "$ref": "#/definitions/handlers.ErrorResponse"
                        }
                    },
                    "500": {
                        "description": "Internal Server Error",
                        "schema": {
                            "$ref": "#/definitions/handlers.ErrorResponse"
                        }
                    }
                }
            },
            "post": {
                "security": [
                    {
                        "BearerAuth": []
                    }
                ],
                "description": "Creates a folder for the authenticated user.",
                "consumes": [
                    "application/json"
                ],
                "produces": [
                    "application/json"
                ],
                "tags": [
                    "folders"
                ],
                "summary": "Create folder",
                "parameters": [
                    {
                        "description": "Create folder request",
                        "name": "request",
                        "in": "body",
                        "required": true,
                        "schema": {
                            "$ref": "#/definitions/handlers.CreateFolderRequest"
                        }
                    }
                ],
                "responses": {
                    "201": {
                        "description": "Created",
                        "schema": {
                            "$ref": "#/definitions/models.Folder"
                        }
                    },
                    "400": {
                        "description": "Bad Request",
                        "schema": {
                            "$ref": "#/definitions/handlers.ErrorResponse"
                        }
                    },
                    "401": {
                        "description": "Unauthorized",
                        "schema": {
                            "$ref": "#/definitions/handlers.ErrorResponse"
                        }
                    },
                    "403": {
                        "description": "Forbidden",
                        "schema": {
                            "$ref": "#/definitions/handlers.ErrorResponse"
                        }
                    },
                    "500": {
                        "description": "Internal Server Error",
                        "schema": {
                            "$ref": "#/definitions/handlers.ErrorResponse"
                        }
                    }
                }
            }
        },
        "/api/folders/{id}": {
            "delete": {
                "security": [
                    {
                        "BearerAuth": []
                    }
                ],
                "description": "Deletes a folder owned by the authenticated user.",
                "tags": [
                    "folders"
                ],
                "summary": "Delete folder",
                "parameters": [
                    {
                        "type": "integer",
                        "description": "Folder ID",
                        "name": "id",
                        "in": "path",
                        "required": true
                    }
                ],
                "responses": {
                    "204": {
                        "description": "No Content",
                        "schema": {
                            "type": "string"
                        }
                    },
                    "400": {
                        "description": "Bad Request",
                        "schema": {
                            "$ref": "#/definitions/handlers.ErrorResponse"
                        }
                    },
                    "401": {
                        "description": "Unauthorized",
                        "schema": {
                            "$ref": "#/definitions/handlers.ErrorResponse"
                        }
                    },
                    "403": {
                        "description": "Forbidden",
                        "schema": {
                            "$ref": "#/definitions/handlers.ErrorResponse"
                        }
                    },
                    "404": {
                        "description": "Not Found",
                        "schema": {
                            "$ref": "#/definitions/handlers.ErrorResponse"
                        }
                    },
                    "500": {
                        "description": "Internal Server Error",
                        "schema": {
                            "$ref": "#/definitions/handlers.ErrorResponse"
                        }
                    }
                }
            },
            "patch": {
                "security": [
                    {
                        "BearerAuth": []
                    }
                ],
                "description": "Updates folder name or parent for the authenticated user.",
                "consumes": [
                    "application/json"
                ],
                "produces": [
                    "application/json"
                ],
                "tags": [
                    "folders"
                ],
                "summary": "Update folder",
                "parameters": [
                    {
                        "type": "integer",
                        "description": "Folder ID",
                        "name": "id",
                        "in": "path",
                        "required": true
                    },
                    {
                        "description": "Update folder request",
                        "name": "request",
                        "in": "body",
                        "required": true,
                        "schema": {
                            "$ref": "#/definitions/handlers.UpdateFolderRequest"
                        }
                    }
                ],
                "responses": {
                    "200": {
                        "description": "OK",
                        "schema": {
                            "$ref": "#/definitions/models.Folder"
                        }
                    },
                    "400": {
                        "description": "Bad Request",
                        "schema": {
                            "$ref": "#/definitions/handlers.ErrorResponse"
                        }
                    },
                    "401": {
                        "description": "Unauthorized",
                        "schema": {
                            "$ref": "#/definitions/handlers.ErrorResponse"
                        }
                    },
                    "403": {
                        "description": "Forbidden",
                        "schema": {
                            "$ref": "#/definitions/handlers.ErrorResponse"
                        }
                    },
                    "404": {
                        "description": "Not Found",
                        "schema": {
                            "$ref": "#/definitions/handlers.ErrorResponse"
                        }
                    },
                    "500": {
                        "description": "Internal Server Error",
                        "schema": {
                            "$ref": "#/definitions/handlers.ErrorResponse"
                        }
                    }
                }
            }
        },
        "/api/images/object": {
            "get": {
                "description": "Streams an image by key using backend credentials.",
                "produces": [
                    "application/octet-stream"
                ],
                "tags": [
                    "images"
                ],
                "summary": "Fetch image from object storage",
                "parameters": [
                    {
                        "type": "string",
                        "description": "Object key",
                        "name": "key",
                        "in": "query",
                        "required": true
                    }
                ],
                "responses": {
                    "200": {
                        "description": "OK",
                        "schema": {
                            "type": "file"
                        }
                    },
                    "400": {
                        "description": "Bad Request",
                        "schema": {
                            "$ref": "#/definitions/handlers.ErrorResponse"
                        }
                    },
                    "404": {
                        "description": "Not Found",
                        "schema": {
                            "$ref": "#/definitions/handlers.ErrorResponse"
                        }
                    },
                    "500": {
                        "description": "Internal Server Error",
                        "schema": {
                            "$ref": "#/definitions/handlers.ErrorResponse"
                        }
                    }
                }
            }
        },
        "/api/images/upload": {
            "post": {
                "description": "Accepts a multipart/form-data payload with a single \"image\" field.",
                "consumes": [
                    "multipart/form-data"
                ],
                "produces": [
                    "application/json"
                ],
                "tags": [
                    "images"
                ],
                "summary": "Upload image to object storage",
                "parameters": [
                    {
                        "type": "file",
                        "description": "Image file (JPEG/PNG/GIF/WEBP, max 5 MiB)",
                        "name": "image",
                        "in": "formData",
                        "required": true
                    }
                ],
                "responses": {
                    "200": {
                        "description": "OK",
                        "schema": {
                            "$ref": "#/definitions/handlers.UploadImageResponse"
                        }
                    },
                    "400": {
                        "description": "Bad Request",
                        "schema": {
                            "$ref": "#/definitions/handlers.ErrorResponse"
                        }
                    },
                    "500": {
                        "description": "Internal Server Error",
                        "schema": {
                            "$ref": "#/definitions/handlers.ErrorResponse"
                        }
                    },
                    "503": {
                        "description": "Service Unavailable",
                        "schema": {
                            "$ref": "#/definitions/handlers.ErrorResponse"
                        }
                    }
                }
            }
        },
        "/api/lobbies": {
            "post": {
                "description": "Creates a new lobby initialized with default map and empty phases.",
                "produces": [
                    "application/json"
                ],
                "tags": [
                    "lobbies"
                ],
                "summary": "Create lobby",
                "responses": {
                    "201": {
                        "description": "Created",
                        "schema": {
                            "$ref": "#/definitions/models.Lobby"
                        }
                    },
                    "500": {
                        "description": "Internal Server Error",
                        "schema": {
                            "$ref": "#/definitions/handlers.ErrorResponse"
                        }
                    }
                }
            }
        },
        "/api/lobbies/{code}": {
            "get": {
                "description": "Retrieves lobby and full canvas phases by lobby code.",
                "produces": [
                    "application/json"
                ],
                "tags": [
                    "lobbies"
                ],
                "summary": "Get lobby",
                "parameters": [
                    {
                        "type": "string",
                        "description": "Lobby code",
                        "name": "code",
                        "in": "path",
                        "required": true
                    }
                ],
                "responses": {
                    "200": {
                        "description": "OK",
                        "schema": {
                            "$ref": "#/definitions/models.Lobby"
                        }
                    },
                    "400": {
                        "description": "Bad Request",
                        "schema": {
                            "$ref": "#/definitions/handlers.ErrorResponse"
                        }
                    },
                    "404": {
                        "description": "Not Found",
                        "schema": {
                            "$ref": "#/definitions/handlers.ErrorResponse"
                        }
                    },
                    "500": {
                        "description": "Internal Server Error",
                        "schema": {
                            "$ref": "#/definitions/handlers.ErrorResponse"
                        }
                    }
                }
            },
            "patch": {
                "description": "Updates lobby canvas state by lobby code.",
                "consumes": [
                    "application/json"
                ],
                "produces": [
                    "application/json"
                ],
                "tags": [
                    "lobbies"
                ],
                "summary": "Update lobby canvas state",
                "parameters": [
                    {
                        "type": "string",
                        "description": "Lobby code",
                        "name": "code",
                        "in": "path",
                        "required": true
                    },
                    {
                        "description": "Canvas update request",
                        "name": "request",
                        "in": "body",
                        "required": true,
                        "schema": {
                            "$ref": "#/definitions/handlers.UpdateLobbyRequest"
                        }
                    }
                ],
                "responses": {
                    "200": {
                        "description": "OK",
                        "schema": {
                            "$ref": "#/definitions/models.Lobby"
                        }
                    },
                    "400": {
                        "description": "Bad Request",
                        "schema": {
                            "$ref": "#/definitions/handlers.ErrorResponse"
                        }
                    },
                    "404": {
                        "description": "Not Found",
                        "schema": {
                            "$ref": "#/definitions/handlers.ErrorResponse"
                        }
                    },
                    "500": {
                        "description": "Internal Server Error",
                        "schema": {
                            "$ref": "#/definitions/handlers.ErrorResponse"
                        }
                    }
                }
            }
        },
        "/api/strategies": {
            "get": {
                "security": [
                    {
                        "BearerAuth": []
                    }
                ],
                "description": "Lists strategies for the authenticated user, optionally filtered by folderId.",
                "produces": [
                    "application/json"
                ],
                "tags": [
                    "strategies"
                ],
                "summary": "List strategies",
                "parameters": [
                    {
                        "type": "integer",
                        "description": "Folder ID filter",
                        "name": "folderId",
                        "in": "query"
                    }
                ],
                "responses": {
                    "200": {
                        "description": "OK",
                        "schema": {
                            "type": "array",
                            "items": {
                                "$ref": "#/definitions/handlers.StrategyResponse"
                            }
                        }
                    },
                    "400": {
                        "description": "Bad Request",
                        "schema": {
                            "$ref": "#/definitions/handlers.ErrorResponse"
                        }
                    },
                    "401": {
                        "description": "Unauthorized",
                        "schema": {
                            "$ref": "#/definitions/handlers.ErrorResponse"
                        }
                    },
                    "500": {
                        "description": "Internal Server Error",
                        "schema": {
                            "$ref": "#/definitions/handlers.ErrorResponse"
                        }
                    }
                }
            },
            "post": {
                "security": [
                    {
                        "BearerAuth": []
                    }
                ],
                "description": "Saves a lobby as a strategy for the authenticated user.",
                "consumes": [
                    "application/json"
                ],
                "produces": [
                    "application/json"
                ],
                "tags": [
                    "strategies"
                ],
                "summary": "Create strategy",
                "parameters": [
                    {
                        "description": "Create strategy request",
                        "name": "request",
                        "in": "body",
                        "required": true,
                        "schema": {
                            "$ref": "#/definitions/handlers.CreateStrategyRequest"
                        }
                    }
                ],
                "responses": {
                    "201": {
                        "description": "Created",
                        "schema": {
                            "$ref": "#/definitions/handlers.StrategyResponse"
                        }
                    },
                    "400": {
                        "description": "Bad Request",
                        "schema": {
                            "$ref": "#/definitions/handlers.ErrorResponse"
                        }
                    },
                    "401": {
                        "description": "Unauthorized",
                        "schema": {
                            "$ref": "#/definitions/handlers.ErrorResponse"
                        }
                    },
                    "403": {
                        "description": "Forbidden",
                        "schema": {
                            "$ref": "#/definitions/handlers.ErrorResponse"
                        }
                    },
                    "404": {
                        "description": "Not Found",
                        "schema": {
                            "$ref": "#/definitions/handlers.ErrorResponse"
                        }
                    },
                    "409": {
                        "description": "Conflict",
                        "schema": {
                            "$ref": "#/definitions/handlers.ErrorResponse"
                        }
                    },
                    "500": {
                        "description": "Internal Server Error",
                        "schema": {
                            "$ref": "#/definitions/handlers.ErrorResponse"
                        }
                    }
                }
            }
        },
        "/api/strategies/{id}": {
            "delete": {
                "security": [
                    {
                        "BearerAuth": []
                    }
                ],
                "description": "Deletes a strategy owned by the authenticated user.",
                "tags": [
                    "strategies"
                ],
                "summary": "Delete strategy",
                "parameters": [
                    {
                        "type": "integer",
                        "description": "Strategy ID",
                        "name": "id",
                        "in": "path",
                        "required": true
                    }
                ],
                "responses": {
                    "204": {
                        "description": "No Content",
                        "schema": {
                            "type": "string"
                        }
                    },
                    "400": {
                        "description": "Bad Request",
                        "schema": {
                            "$ref": "#/definitions/handlers.ErrorResponse"
                        }
                    },
                    "401": {
                        "description": "Unauthorized",
                        "schema": {
                            "$ref": "#/definitions/handlers.ErrorResponse"
                        }
                    },
                    "403": {
                        "description": "Forbidden",
                        "schema": {
                            "$ref": "#/definitions/handlers.ErrorResponse"
                        }
                    },
                    "404": {
                        "description": "Not Found",
                        "schema": {
                            "$ref": "#/definitions/handlers.ErrorResponse"
                        }
                    },
                    "500": {
                        "description": "Internal Server Error",
                        "schema": {
                            "$ref": "#/definitions/handlers.ErrorResponse"
                        }
                    }
                }
            },
            "patch": {
                "security": [
                    {
                        "BearerAuth": []
                    }
                ],
                "description": "Updates strategy name and/or folder assignment.",
                "consumes": [
                    "application/json"
                ],
                "produces": [
                    "application/json"
                ],
                "tags": [
                    "strategies"
                ],
                "summary": "Update strategy",
                "parameters": [
                    {
                        "type": "integer",
                        "description": "Strategy ID",
                        "name": "id",
                        "in": "path",
                        "required": true
                    },
                    {
                        "description": "Update strategy request",
                        "name": "request",
                        "in": "body",
                        "required": true,
                        "schema": {
                            "$ref": "#/definitions/handlers.UpdateStrategyRequest"
                        }
                    }
                ],
                "responses": {
                    "200": {
                        "description": "OK",
                        "schema": {
                            "$ref": "#/definitions/handlers.StrategyResponse"
                        }
                    },
                    "400": {
                        "description": "Bad Request",
                        "schema": {
                            "$ref": "#/definitions/handlers.ErrorResponse"
                        }
                    },
                    "401": {
                        "description": "Unauthorized",
                        "schema": {
                            "$ref": "#/definitions/handlers.ErrorResponse"
                        }
                    },
                    "403": {
                        "description": "Forbidden",
                        "schema": {
                            "$ref": "#/definitions/handlers.ErrorResponse"
                        }
                    },
                    "404": {
                        "description": "Not Found",
                        "schema": {
                            "$ref": "#/definitions/handlers.ErrorResponse"
                        }
                    },
                    "500": {
                        "description": "Internal Server Error",
                        "schema": {
                            "$ref": "#/definitions/handlers.ErrorResponse"
                        }
                    }
                }
            }
        },
        "/api/users": {
            "post": {
                "security": [
                    {
                        "BearerAuth": []
                    }
                ],
                "description": "Creates a user profile linked to the authenticated Firebase UID.",
                "consumes": [
                    "application/json"
                ],
                "produces": [
                    "application/json"
                ],
                "tags": [
                    "users"
                ],
                "summary": "Create user profile",
                "parameters": [
                    {
                        "description": "Create user request",
                        "name": "request",
                        "in": "body",
                        "required": true,
                        "schema": {
                            "$ref": "#/definitions/handlers.CreateUserRequest"
                        }
                    }
                ],
                "responses": {
                    "201": {
                        "description": "Created",
                        "schema": {
                            "$ref": "#/definitions/models.User"
                        }
                    },
                    "400": {
                        "description": "Bad Request",
                        "schema": {
                            "$ref": "#/definitions/handlers.ErrorResponse"
                        }
                    },
                    "401": {
                        "description": "Unauthorized",
                        "schema": {
                            "$ref": "#/definitions/handlers.ErrorResponse"
                        }
                    },
                    "403": {
                        "description": "Forbidden",
                        "schema": {
                            "$ref": "#/definitions/handlers.ErrorResponse"
                        }
                    },
                    "409": {
                        "description": "Conflict",
                        "schema": {
                            "$ref": "#/definitions/handlers.ErrorResponse"
                        }
                    },
                    "500": {
                        "description": "Internal Server Error",
                        "schema": {
                            "$ref": "#/definitions/handlers.ErrorResponse"
                        }
                    }
                }
            }
        },
        "/api/users/me": {
            "get": {
                "security": [
                    {
                        "BearerAuth": []
                    }
                ],
                "description": "Returns the authenticated user's profile.",
                "produces": [
                    "application/json"
                ],
                "tags": [
                    "users"
                ],
                "summary": "Get current user",
                "responses": {
                    "200": {
                        "description": "OK",
                        "schema": {
                            "$ref": "#/definitions/models.User"
                        }
                    },
                    "401": {
                        "description": "Unauthorized",
                        "schema": {
                            "$ref": "#/definitions/handlers.ErrorResponse"
                        }
                    },
                    "500": {
                        "description": "Internal Server Error",
                        "schema": {
                            "$ref": "#/definitions/handlers.ErrorResponse"
                        }
                    }
                }
            },
            "put": {
                "security": [
                    {
                        "BearerAuth": []
                    }
                ],
                "description": "Updates profile fields for the authenticated user.",
                "consumes": [
                    "application/json"
                ],
                "produces": [
                    "application/json"
                ],
                "tags": [
                    "users"
                ],
                "summary": "Update current user",
                "parameters": [
                    {
                        "description": "Update user request",
                        "name": "request",
                        "in": "body",
                        "required": true,
                        "schema": {
                            "$ref": "#/definitions/handlers.UpdateUserRequest"
                        }
                    }
                ],
                "responses": {
                    "200": {
                        "description": "OK",
                        "schema": {
                            "$ref": "#/definitions/models.User"
                        }
                    },
                    "400": {
                        "description": "Bad Request",
                        "schema": {
                            "$ref": "#/definitions/handlers.ErrorResponse"
                        }
                    },
                    "401": {
                        "description": "Unauthorized",
                        "schema": {
                            "$ref": "#/definitions/handlers.ErrorResponse"
                        }
                    },
                    "500": {
                        "description": "Internal Server Error",
                        "schema": {
                            "$ref": "#/definitions/handlers.ErrorResponse"
                        }
                    }
                }
            },
            "delete": {
                "security": [
                    {
                        "BearerAuth": []
                    }
                ],
                "description": "Deletes the authenticated user from the application and Firebase.",
                "tags": [
                    "users"
                ],
                "summary": "Delete current user",
                "responses": {
                    "204": {
                        "description": "No Content",
                        "schema": {
                            "type": "string"
                        }
                    },
                    "401": {
                        "description": "Unauthorized",
                        "schema": {
                            "$ref": "#/definitions/handlers.ErrorResponse"
                        }
                    },
                    "500": {
                        "description": "Internal Server Error",
                        "schema": {
                            "$ref": "#/definitions/handlers.ErrorResponse"
                        }
                    }
                }
            }
        },
        "/api/users/subscription": {
            "patch": {
                "security": [
                    {
                        "InternalAPIKey": []
                    }
                ],
                "description": "Internal endpoint to update a user's subscription status by userId or firebaseUid.",
                "consumes": [
                    "application/json"
                ],
                "produces": [
                    "application/json"
                ],
                "tags": [
                    "users"
                ],
                "summary": "Update user subscription status",
                "parameters": [
                    {
                        "type": "string",
                        "description": "Internal API key",
                        "name": "X-Internal-API-Key",
                        "in": "header",
                        "required": true
                    },
                    {
                        "description": "Subscription update request",
                        "name": "request",
                        "in": "body",
                        "required": true,
                        "schema": {
                            "$ref": "#/definitions/handlers.UpdateUserSubscriptionRequest"
                        }
                    }
                ],
                "responses": {
                    "200": {
                        "description": "OK",
                        "schema": {
                            "$ref": "#/definitions/models.User"
                        }
                    },
                    "400": {
                        "description": "Bad Request",
                        "schema": {
                            "$ref": "#/definitions/handlers.ErrorResponse"
                        }
                    },
                    "403": {
                        "description": "Forbidden",
                        "schema": {
                            "$ref": "#/definitions/handlers.ErrorResponse"
                        }
                    },
                    "404": {
                        "description": "Not Found",
                        "schema": {
                            "$ref": "#/definitions/handlers.ErrorResponse"
                        }
                    },
                    "500": {
                        "description": "Internal Server Error",
                        "schema": {
                            "$ref": "#/definitions/handlers.ErrorResponse"
                        }
                    }
                }
            }
        },
        "/health": {
            "get": {
                "description": "Checks API and database connectivity.",
                "produces": [
                    "text/plain"
                ],
                "tags": [
                    "health"
                ],
                "summary": "Health check",
                "responses": {
                    "200": {
                        "description": "OK",
                        "schema": {
                            "type": "string"
                        }
                    },
                    "503": {
                        "description": "Database unavailable",
                        "schema": {
                            "type": "string"
                        }
                    }
                }
            }
        }
    },
    "definitions": {
        "handlers.BillingPlanPriceResponse": {
            "type": "object",
            "properties": {
                "currency": {
                    "type": "string"
                },
                "interval": {
                    "type": "string"
                },
                "intervalCount": {
                    "type": "integer"
                },
                "plan": {
                    "type": "string"
                },
                "priceId": {
                    "type": "string"
                },
                "unitAmount": {
                    "type": "integer"
                },
                "unitAmountDecimal": {
                    "type": "string"
                }
            }
        },
        "handlers.BillingPlansResponse": {
            "type": "object",
            "properties": {
                "monthly": {
                    "$ref": "#/definitions/handlers.BillingPlanPriceResponse"
                },
                "stack": {
                    "$ref": "#/definitions/handlers.BillingPlanPriceResponse"
                },
                "yearly": {
                    "$ref": "#/definitions/handlers.BillingPlanPriceResponse"
                }
            }
        },
        "handlers.CancelSubscriptionResponse": {
            "type": "object",
            "properties": {
                "cancelAtPeriodEnd": {
                    "type": "boolean"
                },
                "status": {
                    "type": "string"
                },
                "subscriptionId": {
                    "type": "string"
                }
            }
        },
        "handlers.CreateCheckoutSessionRequest": {
            "type": "object",
            "properties": {
                "plan": {
                    "type": "string"
                },
                "returnTo": {
                    "type": "string"
                },
                "startWithTrial": {
                    "type": "boolean"
                }
            }
        },
        "handlers.CreateCheckoutSessionResponse": {
            "type": "object",
            "properties": {
                "sessionId": {
                    "type": "string"
                },
                "url": {
                    "type": "string"
                }
            }
        },
        "handlers.CreateFolderRequest": {
            "type": "object",
            "properties": {
                "name": {
                    "type": "string"
                },
                "parentFolderId": {
                    "type": "integer"
                }
            }
        },
        "handlers.CreateStrategyRequest": {
            "type": "object",
            "properties": {
                "folderId": {
                    "type": "integer"
                },
                "lobbyCode": {
                    "type": "string"
                },
                "name": {
                    "type": "string"
                }
            }
        },
        "handlers.CreateUserRequest": {
            "type": "object",
            "properties": {
                "email": {
                    "type": "string"
                },
                "firebaseUid": {
                    "type": "string"
                },
                "name": {
                    "type": "string"
                }
            }
        },
        "handlers.ErrorResponse": {
            "type": "object",
            "properties": {
                "error": {
                    "type": "string"
                },
                "requestId": {
                    "type": "string"
                }
            }
        },
        "handlers.InviteStackMemberRequest": {
            "type": "object",
            "properties": {
                "firebaseUid": {
                    "type": "string"
                }
            }
        },
        "handlers.RSOCallbackResponse": {
            "type": "object",
            "properties": {
                "customToken": {
                    "type": "string"
                },
                "user": {
                    "$ref": "#/definitions/models.User"
                }
            }
        },
        "handlers.RSORequest": {
            "type": "object",
            "properties": {
                "code": {
                    "type": "string"
                }
            }
        },
        "handlers.StackMembersResponse": {
            "type": "object",
            "properties": {
                "canManage": {
                    "type": "boolean"
                },
                "members": {
                    "type": "array",
                    "items": {
                        "$ref": "#/definitions/models.StackMember"
                    }
                },
                "owner": {
                    "$ref": "#/definitions/handlers.StackOwnerResponse"
                }
            }
        },
        "handlers.StackOwnerResponse": {
            "type": "object",
            "properties": {
                "email": {
                    "type": "string"
                },
                "name": {
                    "type": "string"
                },
                "userId": {
                    "type": "integer"
                }
            }
        },
        "handlers.StrategyResponse": {
            "type": "object",
            "properties": {
                "folderId": {
                    "type": "integer"
                },
                "id": {
                    "type": "integer"
                },
                "lobbyCode": {
                    "type": "string"
                },
                "name": {
                    "type": "string"
                },
                "selectedMapId": {
                    "type": "string"
                },
                "updatedAt": {
                    "type": "string"
                },
                "userId": {
                    "type": "integer"
                }
            }
        },
        "handlers.StripeWebhookResponse": {
            "type": "object",
            "properties": {
                "eventId": {
                    "type": "string"
                },
                "eventType": {
                    "type": "string"
                },
                "reason": {
                    "type": "string"
                },
                "status": {
                    "type": "string"
                }
            }
        },
        "handlers.UpdateFolderRequest": {
            "type": "object",
            "properties": {
                "name": {
                    "type": "string"
                },
                "parentFolderId": {
                    "type": "integer"
                }
            }
        },
        "handlers.UpdateLobbyRequest": {
            "type": "object",
            "properties": {
                "canvasState": {
                    "$ref": "#/definitions/models.FullCanvasState"
                }
            }
        },
        "handlers.UpdateStrategyRequest": {
            "type": "object",
            "properties": {
                "folderId": {
                    "type": "integer"
                },
                "name": {
                    "type": "string"
                }
            }
        },
        "handlers.UpdateUserRequest": {
            "type": "object",
            "properties": {
                "name": {
                    "type": "string"
                },
                "tourCompleted": {
                    "type": "boolean"
                }
            }
        },
        "handlers.UpdateUserSubscriptionRequest": {
            "type": "object",
            "properties": {
                "firebaseUid": {
                    "type": "string"
                },
                "isSubscribed": {
                    "type": "boolean"
                },
                "userId": {
                    "type": "integer"
                }
            }
        },
        "handlers.UploadImageResponse": {
            "type": "object",
            "properties": {
                "key": {
                    "type": "string"
                },
                "url": {
                    "type": "string"
                }
            }
        },
        "models.CanvasAbility": {
            "type": "object",
            "properties": {
                "action": {
                    "type": "string"
                },
                "currentLength": {
                    "type": "number"
                },
                "currentPath": {
                    "type": "array",
                    "items": {
                        "$ref": "#/definitions/models.Position"
                    }
                },
                "currentRotation": {
                    "type": "number"
                },
                "iconOnly": {
                    "type": "boolean"
                },
                "id": {
                    "type": "string"
                },
                "isAlly": {
                    "type": "boolean"
                },
                "name": {
                    "type": "string"
                },
                "showOuterCircle": {
                    "type": "boolean"
                },
                "x": {
                    "type": "number"
                },
                "y": {
                    "type": "number"
                }
            }
        },
        "models.CanvasAgent": {
            "type": "object",
            "properties": {
                "id": {
                    "type": "string"
                },
                "isAlly": {
                    "type": "boolean"
                },
                "name": {
                    "type": "string"
                },
                "role": {
                    "type": "string"
                },
                "x": {
                    "type": "number"
                },
                "y": {
                    "type": "number"
                }
            }
        },
        "models.CanvasConnectingLine": {
            "type": "object",
            "properties": {
                "fromId": {
                    "type": "string"
                },
                "id": {
                    "type": "string"
                },
                "notes": {
                    "type": "string"
                },
                "strokeColor": {
                    "type": "string"
                },
                "strokeWidth": {
                    "type": "number"
                },
                "toId": {
                    "type": "string"
                },
                "uploadedImages": {
                    "type": "array",
                    "items": {
                        "type": "string"
                    }
                },
                "youtubeLink": {
                    "type": "string"
                }
            }
        },
        "models.CanvasDrawLine": {
            "type": "object",
            "properties": {
                "color": {
                    "type": "string"
                },
                "id": {
                    "type": "string"
                },
                "isArrowHead": {
                    "type": "boolean"
                },
                "isDashed": {
                    "type": "boolean"
                },
                "points": {
                    "type": "array",
                    "items": {
                        "$ref": "#/definitions/models.Position"
                    }
                },
                "size": {
                    "type": "number"
                },
                "tool": {
                    "type": "string"
                }
            }
        },
        "models.CanvasImage": {
            "type": "object",
            "properties": {
                "height": {
                    "type": "number"
                },
                "id": {
                    "type": "string"
                },
                "src": {
                    "type": "string"
                },
                "width": {
                    "type": "number"
                },
                "x": {
                    "type": "number"
                },
                "y": {
                    "type": "number"
                }
            }
        },
        "models.CanvasText": {
            "type": "object",
            "properties": {
                "height": {
                    "type": "number"
                },
                "id": {
                    "type": "string"
                },
                "text": {
                    "type": "string"
                },
                "width": {
                    "type": "number"
                },
                "x": {
                    "type": "number"
                },
                "y": {
                    "type": "number"
                }
            }
        },
        "models.CanvasToolIcon": {
            "type": "object",
            "properties": {
                "height": {
                    "type": "number"
                },
                "id": {
                    "type": "string"
                },
                "name": {
                    "type": "string"
                },
                "width": {
                    "type": "number"
                },
                "x": {
                    "type": "number"
                },
                "y": {
                    "type": "number"
                }
            }
        },
        "models.Folder": {
            "type": "object",
            "properties": {
                "createdAt": {
                    "type": "string"
                },
                "id": {
                    "type": "integer"
                },
                "name": {
                    "type": "string"
                },
                "parentFolderId": {
                    "type": "integer"
                },
                "updatedAt": {
                    "type": "string"
                },
                "userId": {
                    "type": "integer"
                }
            }
        },
        "models.FullCanvasState": {
            "type": "object",
            "properties": {
                "abilitiesSettings": {
                    "$ref": "#/definitions/models.IconSettings"
                },
                "agentsSettings": {
                    "$ref": "#/definitions/models.IconSettings"
                },
                "currentPhaseIndex": {
                    "type": "integer"
                },
                "editedPhases": {
                    "type": "array",
                    "items": {
                        "type": "integer"
                    }
                },
                "mapSide": {
                    "type": "string"
                },
                "phases": {
                    "type": "array",
                    "items": {
                        "$ref": "#/definitions/models.PhaseState"
                    }
                },
                "selectedMap": {
                    "$ref": "#/definitions/models.MapOption"
                }
            }
        },
        "models.IconSettings": {
            "type": "object",
            "properties": {
                "allyColor": {
                    "type": "string"
                },
                "borderOpacity": {
                    "type": "number"
                },
                "borderWidth": {
                    "type": "integer"
                },
                "enemyColor": {
                    "type": "string"
                },
                "radius": {
                    "type": "integer"
                },
                "scale": {
                    "type": "integer"
                }
            }
        },
        "models.Lobby": {
            "type": "object",
            "properties": {
                "canvasState": {
                    "$ref": "#/definitions/models.FullCanvasState"
                },
                "createdAt": {
                    "type": "string"
                },
                "lobbyCode": {
                    "type": "string"
                },
                "mapSide": {
                    "type": "string"
                },
                "selectedMapId": {
                    "type": "string"
                },
                "updatedAt": {
                    "type": "string"
                }
            }
        },
        "models.MapOption": {
            "type": "object",
            "properties": {
                "id": {
                    "type": "string"
                },
                "text": {
                    "type": "string"
                },
                "textColor": {
                    "type": "string"
                }
            }
        },
        "models.PhaseState": {
            "type": "object",
            "properties": {
                "abilitiesOnCanvas": {
                    "type": "array",
                    "items": {
                        "$ref": "#/definitions/models.CanvasAbility"
                    }
                },
                "agentsOnCanvas": {
                    "type": "array",
                    "items": {
                        "$ref": "#/definitions/models.CanvasAgent"
                    }
                },
                "connectingLines": {
                    "type": "array",
                    "items": {
                        "$ref": "#/definitions/models.CanvasConnectingLine"
                    }
                },
                "drawLines": {
                    "type": "array",
                    "items": {
                        "$ref": "#/definitions/models.CanvasDrawLine"
                    }
                },
                "imagesOnCanvas": {
                    "type": "array",
                    "items": {
                        "$ref": "#/definitions/models.CanvasImage"
                    }
                },
                "textsOnCanvas": {
                    "type": "array",
                    "items": {
                        "$ref": "#/definitions/models.CanvasText"
                    }
                },
                "toolIconsOnCanvas": {
                    "type": "array",
                    "items": {
                        "$ref": "#/definitions/models.CanvasToolIcon"
                    }
                }
            }
        },
        "models.Position": {
            "type": "object",
            "properties": {
                "x": {
                    "type": "number"
                },
                "y": {
                    "type": "number"
                }
            }
        },
        "models.StackMember": {
            "type": "object",
            "properties": {
                "id": {
                    "type": "integer"
                },
                "invitedAt": {
                    "type": "string"
                },
                "joinedAt": {
                    "type": "string"
                },
                "memberEmail": {
                    "description": "Populated via JOIN when listing members",
                    "type": "string"
                },
                "memberName": {
                    "type": "string"
                },
                "memberUserId": {
                    "type": "integer"
                },
                "ownerEmail": {
                    "type": "string"
                },
                "ownerName": {
                    "type": "string"
                },
                "ownerUserId": {
                    "type": "integer"
                },
                "status": {
                    "type": "string"
                }
            }
        },
        "models.User": {
            "type": "object",
            "properties": {
                "createdAt": {
                    "type": "string"
                },
                "email": {
                    "type": "string"
                },
                "emailVerified": {
                    "type": "boolean"
                },
                "firebaseUid": {
                    "type": "string"
                },
                "id": {
                    "type": "integer"
                },
                "isSubscribed": {
                    "type": "boolean"
                },
                "name": {
                    "type": "string"
                },
                "premiumTrialDaysLeft": {
                    "type": "integer"
                },
                "premiumTrialEligible": {
                    "type": "boolean"
                },
                "rsoLinkedAt": {
                    "type": "string"
                },
                "rsoSubjectId": {
                    "type": "string"
                },
                "subscriptionEndedAt": {
                    "type": "string"
                },
                "subscriptionPlan": {
                    "type": "string"
                },
                "tourCompleted": {
                    "type": "boolean"
                },
                "updatedAt": {
                    "type": "string"
                }
            }
        }
    },
    "securityDefinitions": {
        "BearerAuth": {
            "description": "Firebase bearer token in the form \"Bearer \u003ctoken\u003e\".",
            "type": "apiKey",
            "name": "Authorization",
            "in": "header"
        },
        "InternalAPIKey": {
            "description": "Internal service API key.",
            "type": "apiKey",
            "name": "X-Internal-API-Key",
            "in": "header"
        }
    }
}